{
  "scene": {
    "Floor|+00.00|+00.00|+00.00": {
      "state": "clear",
      "pose": [
        []
      ],
      "camera_pose": 30,
      "crouch": "False",
      "contains": [
        "Agent"
      ]
    },
    "Drawer|+00.87|+00.75|-01.14": {
      "state": "Closed",
      "pose": [
        []
      ],
      "camera_pose": 30,
      "crouch": "False",
      "contains": [
        "Apple|+00.99|+00.94|-01.11",
        "Cup|+01.10|+00.90|-00.93"
      ]
    },
    "CounterTop|+01.17|+00.95|-00.65": {
      "state": "clear",
      "pose": [
        []
      ],
      "camera_pose": 30,
      "crouch": "False",
      "contains": [
        "Bowl|+01.02|+00.90|-00.52",
        "Bread|+01.16|+00.98|-00.16",
        "Lettuce|+00.51|+00.95|-01.58",
        "Microwave|+01.42|+01.15|+00.02",
        "Pot|+00.97|+00.90|+00.25",
        "Sink|+00.16|+00.82|-01.80"
      ]
    },
    "Cabinet|-00.82|+00.40|-01.39": {
      "state": "Closed",
      "pose": [
        []
      ],
      "camera_pose": 30,
      "crouch": "False",
      "contains": [
        "ButterKnife|-00.66|+00.90|-01.72"
      ]
    },
    "Cabinet|-00.87|+02.01|-01.69": {
      "state": "Closed",
      "pose": [
        []
      ],
      "camera_pose": 30,
      "crouch": "False",
      "contains": []
    },
    "Cabinet|-00.20|+00.40|-01.39": {
      "state": "Closed",
      "pose": [
        []
      ],
      "camera_pose": 30,
      "crouch": "False",
      "contains": [
        "SprayBottle|-00.01|+00.10|-01.55"
      ]
    },
    "Cabinet|+00.83|+00.40|-01.39": {
      "state": "Closed",
      "pose": [
        []
      ],
      "camera_pose": 30,
      "crouch": "False",
      "contains": [
        "Kettle|+00.77|+00.90|-01.84"
      ]
    },
    "Cabinet|-01.61|+02.01|-01.69": {
      "state": "Closed",
      "pose": [
        []
      ],
      "camera_pose": 30,
      "crouch": "False",
      "contains": []
    },
    "Cabinet|+01.16|+02.06|-01.02": {
      "state": "Closed",
      "pose": [
        []
      ],
      "camera_pose": 30,
      "crouch": "False",
      "contains": []
    },
    "Cabinet|-01.67|+00.40|-01.39": {
      "state": "Closed",
      "pose": [
        []
      ],
      "camera_pose": 30,
      "crouch": "False",
      "contains": []
    },
    "Cabinet|-02.24|+00.40|-01.39": {
      "state": "Closed",
      "pose": [
        []
      ],
      "camera_pose": 30,
      "crouch": "False",
      "contains": []
    },
    "Cabinet|-00.19|+02.06|-01.69": {
      "state": "Closed",
      "pose": [
        []
      ],
      "camera_pose": 30,
      "crouch": "False",
      "contains": []
    },
    "Cabinet|-00.24|+00.40|-01.39": {
      "state": "Closed",
      "pose": [
        []
      ],
      "camera_pose": 30,
      "crouch": "False",
      "contains": []
    },
    "Cabinet|+00.86|+00.40|-01.37": {
      "state": "Closed",
      "pose": [
        []
      ],
      "camera_pose": 30,
      "crouch": "False",
      "contains": []
    },
    "Cabinet|+00.86|+00.40|-00.55": {
      "state": "Closed",
      "pose": [
        []
      ],
      "camera_pose": 30,
      "crouch": "False",
      "contains": []
    },
    "Cabinet|+00.86|+00.40|+00.67": {
      "state": "Closed",
      "pose": [
        []
      ],
      "camera_pose": 30,
      "crouch": "False",
      "contains": []
    },
    "Cabinet|-00.82|+02.06|-01.69": {
      "state": "Closed",
      "pose": [
        []
      ],
      "camera_pose": 30,
      "crouch": "False",
      "contains": []
    },
    "Cabinet|-01.66|+02.06|-01.68": {
      "state": "Closed",
      "pose": [
        []
      ],
      "camera_pose": 30,
      "crouch": "False",
      "contains": []
    },
    "Cabinet|+00.49|+02.06|-01.69": {
      "state": "Closed",
      "pose": [
        []
      ],
      "camera_pose": 30,
      "crouch": "False",
      "contains": []
    },
    "Cabinet|+01.16|+02.06|-00.34": {
      "state": "Closed",
      "pose": [
        []
      ],
      "camera_pose": 30,
      "crouch": "False",
      "contains": []
    },
    "Microwave|+01.42|+01.15|+00.02": {
      "state": "Closed",
      "pose": [
        []
      ],
      "camera_pose": 30,
      "crouch": "False",
      "contains": [
        "CounterTop|+01.50|+01.20|-00.66",
        "CounterTop|+01.17|+00.95|-00.65"
      ]
    },
    "Bowl|+01.02|+00.90|-00.52": {
      "state": "clear",
      "pose": [
        []
      ],
      "camera_pose": 30,
      "crouch": "False",
      "contains": [
        "CounterTop|+01.17|+00.95|-00.65"
      ]
    },
    "Pot|+00.97|+00.90|+00.25": {
      "state": "clear",
      "pose": [
        []
      ],
      "camera_pose": 30,
      "crouch": "False",
      "contains": [
        "CounterTop|+01.17|+00.95|-00.65",
        "Drawer|+00.86|+00.75|+00.43"
      ]
    },
    "Drawer|-00.69|+00.75|-01.39": {
      "state": "Closed",
      "pose": [
        []
      ],
      "camera_pose": 30,
      "crouch": "False",
      "contains": [
        "Fork|-00.69|+00.90|-01.55"
      ]
    },
    "Drawer|-02.11|+00.75|-01.39": {
      "state": "Closed",
      "pose": [
        []
      ],
      "camera_pose": 30,
      "crouch": "False",
      "contains": []
    },
    "Drawer|+00.59|+00.75|-01.39": {
      "state": "Closed",
      "pose": [
        []
      ],
      "camera_pose": 30,
      "crouch": "False",
      "contains": [
        "Lettuce|+00.51|+00.95|-01.58"
      ]
    },
    "Drawer|-00.38|+00.75|-01.39": {
      "state": "Closed",
      "pose": [
        []
      ],
      "camera_pose": 30,
      "crouch": "False",
      "contains": []
    },
    "Drawer|+00.86|+00.75|-00.70": {
      "state": "Closed",
      "pose": [
        []
      ],
      "camera_pose": 30,
      "crouch": "False",
      "contains": []
    },
    "Drawer|-01.80|+00.75|-01.39": {
      "state": "Closed",
      "pose": [
        []
      ],
      "camera_pose": 30,
      "crouch": "False",
      "contains": []
    },
    "Drawer|+00.86|+00.75|+00.43": {
      "state": "Closed",
      "pose": [
        []
      ],
      "camera_pose": 30,
      "crouch": "False",
      "contains": [
        "Knife|+01.04|+00.91|+00.44",
        "Pot|+00.97|+00.90|+00.25"
      ]
    },
    "Sink|+00.16|+00.82|-01.80": {
      "state": "clear",
      "pose": [
        []
      ],
      "camera_pose": 30,
      "crouch": "False",
      "contains": [
        "Egg|+00.30|+00.93|-01.61"
      ]
    },
    "Floor|+04.06|+00.00|-00.71": {
      "state": "clear",
      "pose": [
        []
      ],
      "camera_pose": 30,
      "crouch": "False",
      "contains": [
        "Fridge|+01.42|+00.00|+02.10",
        "GarbageCan|+01.34|+00.02|+01.04",
        "Ladle|-01.84|+00.93|+00.09",
        "Pen|-02.36|+00.91|+00.55",
        "Stool|-01.99|+00.01|+00.88",
        "Tomato|-01.82|+00.94|+00.43"
      ]
    },
    "Fridge|+01.42|+00.00|+02.10": {
      "state": "Closed",
      "pose": [
        []
      ],
      "camera_pose": 30,
      "crouch": "False",
      "contains": []
    },
    "Kettle|+00.77|+00.90|-01.84": {
      "state": "Closed",
      "pose": [
        []
      ],
      "camera_pose": 30,
      "crouch": "False",
      "contains": []
    },
    "CounterTop|+01.50|+01.20|-00.66": {
      "state": "clear",
      "pose": [
        []
      ],
      "camera_pose": 30,
      "crouch": "False",
      "contains": [
        "Microwave|+01.42|+01.15|+00.02"
      ]
    },
    "Plate|+01.43|+01.15|-00.54": {
      "state": "clear",
      "pose": [
        []
      ],
      "camera_pose": 30,
      "crouch": "False",
      "contains": [
        "Mug|+01.45|+01.65|-00.52"
      ]
    },
    "StoveBurner|-01.08|+00.94|-01.53": {
      "state": "clear",
      "pose": [
        []
      ],
      "camera_pose": 30,
      "crouch": "False",
      "contains": [
        "Pan|-01.08|+00.95|-01.53"
      ]
    },
    "CounterTop|-01.97|+00.95|-01.71": {
      "state": "clear",
      "pose": [
        []
      ],
      "camera_pose": 30,
      "crouch": "False",
      "contains": [
        "PepperShaker|-01.70|+00.90|-01.84",
        "SaltShaker|-01.77|+00.90|-01.68",
        "Spatula|-01.95|+00.91|-01.53",
        "Toaster|-02.07|+00.90|-01.85"
      ]
    },
    "Stove": {
      "state": "clear",
      "pose": [
        []
      ],
      "camera_pose": 30,
      "crouch": "False",
      "contains": [
        "StoveBurner|-01.08|+00.94|-01.81",
        "StoveBurner|-01.43|+00.94|-01.53",
        "StoveBurner|-01.08|+00.94|-01.53",
        "StoveBurner|-01.43|+00.94|-01.81",
        "StoveKnob|-01.52|+01.10|-01.98",
        "StoveKnob|-00.96|+01.10|-01.98",
        "StoveKnob|-01.11|+01.10|-01.98",
        "StoveKnob|-01.36|+01.10|-01.98"
      ]
    }
  }
}